django_getpaid_epay-0.1.4.dist-info/METADATA
django_getpaid_epay-0.1.4.dist-info/RECORD
django_getpaid_epay-0.1.4.dist-info/DESCRIPTION.rst
django_getpaid_epay-0.1.4.dist-info/top_level.txt
django_getpaid_epay-0.1.4.dist-info/metadata.json
django_getpaid_epay-0.1.4.dist-info/WHEEL
epay/views.py
epay/__init__.py
epay/models.py
epay/admin.py
epay/urls.py
epay/kkb/utils.py
epay/kkb/signing.py
epay/kkb/__init__.py
epay/kkb/processing.py
epay/kkb/exceptions.py
epay/keys/kkbca.pem
epay/keys/cert.pem
epay/templates/epay/payment_detail.html
epay/static/epay/img/logo.png
epay/migrations/0001_initial.py
epay/migrations/__init__.py
