Metadata-Version: 2.0
Name: django-getpaid-epay
Version: 0.1.4
Summary: A django-getpaid payment backend for Kazkommertsbank Epay
Home-page: https://github.com/yunmanger1/django-getpaid-epay
Author: German Ilyin
Author-email: germanilyin@gmail.com
License: BSD
Keywords: django-getpaid-epay
Platform: UNKNOWN
Classifier: Development Status :: 3 - Alpha
Classifier: Framework :: Django
Classifier: Framework :: Django :: 1.8
Classifier: Framework :: Django :: 1.9
Classifier: Intended Audience :: Developers
Classifier: License :: OSI Approved :: BSD License
Classifier: Natural Language :: English
Classifier: Programming Language :: Python :: 2
Classifier: Programming Language :: Python :: 2.7
Classifier: Programming Language :: Python :: 3
Classifier: Programming Language :: Python :: 3.3
Classifier: Programming Language :: Python :: 3.4
Classifier: Programming Language :: Python :: 3.5
Requires-Dist: django-getpaid (>=1.7.4)
Requires-Dist: django-model-utils
Requires-Dist: xmltodict
Requires-Dist: M2Crypto
